pypitester/__init__.py
pypitester/cli.py
pypitester/utils.py
pypitester-0.1.2.dist-info/entry_points.txt
pypitester-0.1.2.dist-info/licenses/LICENSE
pypitester-0.1.2.dist-info/WHEEL
pypitester-0.1.2.dist-info/METADATA
pypitester-0.1.2.dist-info/RECORD
