Metadata-Version: 2.4
Name: pypitester
Version: 0.1.2
Summary: A simple Python package for PyPI testing.
Author-email: Test User <test@example.com>
Classifier: Development Status :: 3 - Alpha
Classifier: Intended Audience :: Developers
Classifier: Programming Language :: Python :: 3
Classifier: Programming Language :: Python :: 3.7
License-File: LICENSE
